gencedula
