Metadata-Version: 2.1
Name: gencedula
Version: 0.4
Summary: Python3 module to generate random and verify uruguay identification document.
Home-page: https://github.com/carlosplanchon/gencedula
Author: Carlos A. Planchón
Author-email: bubbledoloresuruguay2@gmail.com
License: GPL3
Download-URL: https://github.com/carlosplanchon/gencedula/archive/v0.4.tar.gz
Keywords: generate,uruguay,identification,document,verify,number,cedula
Platform: UNKNOWN
Classifier: Intended Audience :: Developers
Classifier: Topic :: Software Development :: Build Tools
Classifier: License :: OSI Approved :: GNU General Public License v3 (GPLv3)
Classifier: Programming Language :: Python :: 3
Classifier: Programming Language :: Python :: 3.4
Classifier: Programming Language :: Python :: 3.5
Classifier: Programming Language :: Python :: 3.6
Classifier: Programming Language :: Python :: 3.7
